{
  "entries": [
    {
      "title": "Apertura XXXV convegno ITM",
      "description": "Teatro di Rossa",
      "start": "2025-09-12T18:00:00"
    },
    {
      "title": "Intervento del coordinatore di Incontri Tra/Montani",
      "description": "Giancarlo Maculotti",
      "start": "2025-09-12T18:30:00"
    },
    {
      "title": "Saluti delle autorità",
      "description": "Sindaco di Balmuccia, Sindaco di Rossa, Sindaco di Boccioleto, Sindaco di Alto Sermenza, Direttrice Ente Parco Aree Protette Alta Valsesia, Presidente UNCEM Nazionale, Presidente UNCEM Piemonte, Presidente della Provincia, Presidente GAL, Assessore alla Cultura Unione Montana, Presidente Unione Montan",
      "start": "2025-09-12T18:45:00",
      "showStart": false
    },
    {
      "title": "Conferenza di Annibale Salsa",
      "description": "L’epopea dei dissodatori: La costruzione del Paesaggio Alpino",
      "start": "2025-09-12T19:00:00"
    },
    {
      "title": "Manuela Baldracchi",
      "description": "L’architettura delle baite di montagna. Espressione autentica dell’autocostruzione",
      "start": "2025-09-13T09:30:00",
      "group": "Attività coordinamento ITM"
    },
    {
      "title": "Invernizzi Pietro",
      "description": "Interventi su edifici, coperture in pietra e murature a secco delle valli bergamasche",
      "start": "2025-09-13T10:00:00",
      "group": "Attività coordinamento ITM"
    },
    {
      "title": "Aldo Fezzi",
      "description": "I terrazzamenti della Valle di Sole: Aspetti storici, attuale utilizzo e prospettive",
      "start": "2025-09-13T10:30:00",
      "group": "Attività coordinamento ITM"
    },
    {
      "title": "Marco Comecini",
      "description": "Architettura popolare Cimbra della Lessinia",
      "start": "2025-09-13T11:00:00",
      "group": "Attività coordinamento ITM"
    },
    {
      "title": "Marco Zulberti",
      "description": "La metamorfosi del paesaggio architettonico",
      "start": "2025-09-13T11:30:00",
      "group": "Attività coordinamento ITM"
    },
    {
      "title": "Pranzo",
      "description": "Presso Foresteria Valsesia, Cerva di Rossa",
      "start": "2025-09-13T12:30:00"
    },
    {
      "title": "Samuele De Filippi",
      "description": "Cantiere Naviledo, Abitare un cantiere",
      "group": "La comunità che costruisce",
      "start": "2025-09-13T14:30:00"
    },
    {
      "title": "Gabriella Burlazzi",
      "description": "Materiali e tecniche nell’edilizia storica montana. Il manuale Gal Valsesia, strumento indispensabile per gli artigiani e i professionisti del recupero dell’edilizia storica",
      "group": "La comunità che costruisce",
      "start": "2025-09-13T15:00:00"
    },
    {
      "title": "Valerio Botta",
      "description": "Le pecore, il villaggio e un’architettura di un futuro possibile. Il caso Vrin",
      "group": "Progettare con la comunità",
      "start": "2025-09-13T15:30:00"
    },
    {
      "title": "Mauro Testini",
      "description": "Rigenerazione sociale dei paesi di montagna. Esperienza di VioneLAB",
      "group": "Progettare con la comunità",
      "start": "2025-09-13T16:00:00"
    },
    {
      "title": "Andrea Staid",
      "description": "Pratiche attuali di autocostruzione",
      "group": "Forme moderne di autocostruzione",
      "start": "2025-09-13T16:30:00"
    },
    {
      "title": "Domande e osservazioni dei partecipanti sulle relazioni e le esperienze vissute durante il convegno",
      "description": "Coordina Giancarlo Maculotti",
      "start": "2025-09-13T17:00:00"
    },
    {
      "title": "Tavola rotonda e riunione finale Coordinamento ITM",
      "start": "2025-09-13T17:30:00"
    },
    {
      "title": "Cena",
      "description": "Presso Trattoria il Giacomaccio, Boccioleto",
      "start": "2025-09-13T19:00:00"
    },
    {
      "title": "Passeggiata storico-etnografica a cura di Roberto Fantoni",
      "description": "Boccioleto-Oro-Rossa",
      "start": "2025-09-14T09:00:00"
    },
    {
      "title": "Visita al Museo del Marmo di Rima",
      "description": "A cura di Roberto Fantoni",
      "title2": "Roberto Fantoni",
      "description2": "Visita al Museo del Marmo di Rima a cura della Pro Loco di Rima",
      "place": "Rima, Alto-Sermenza",
      "start": "2025-09-14T11:00:00"
    },
    {
      "title": "ANAB",
      "description": "Conferenza ‘I principi dell’architettura naturale: casi studio nell’arco alpino",
      "start": "2025-09-14T10:00:00",
      "end": "2025-09-14T12:00:00"
    },
    {
      "title": "Pranzo",
      "description": "Presso Ristorante Alpino, Rima, Alto-Sermenza",
      "start": "2025-09-14T13:00:00"
    },
    {
      "title": "ANAB",
      "description": "Seminari dimostrativi sull’edilizia sostenibile - Frazione Piana di Rossa",
      "place": "Frazione Piana di Rossa",
      "start": "2025-09-14T14:30:00"
    },
    {
      "title": "Visita alla ‘Casa del Falegname’",
      "description": "FAI Valsesia - Frazione Piana di Rossa",
      "place": "Frazione Piana di Rossa",
      "start": "2025-09-14T16:00:00"
    },
    {
      "title": "Proiezione del docu-film ‘La ruota sospesa’",
      "description": "FAI Valsesia - Teatro di Rossa",
      "start": "2025-09-14T17:30:00"
    }
  ]
}
